{
  "stats": {
    "suites": 6,
    "tests": 29,
    "passes": 29,
    "pending": 0,
    "failures": 0,
    "start": "2022-07-13T14:42:13.587Z",
    "end": "2022-07-13T14:43:04.406Z",
    "duration": 21485,
    "testsRegistered": 29,
    "passPercent": 100,
    "pendingPercent": 0,
    "other": 0,
    "hasOther": false,
    "skipped": 0,
    "hasSkipped": false
  },
  "results": [
    {
      "uuid": "b7396631-6472-45d1-bf50-52f8292814be",
      "title": "",
      "fullFile": "",
      "file": "",
      "beforeHooks": [],
      "afterHooks": [],
      "tests": [],
      "suites": [
        {
          "uuid": "5dd99340-ecb7-42bf-b492-ceb290f3f65b",
          "title": "Main Menu Tabs",
          "fullFile": "",
          "file": "",
          "beforeHooks": [],
          "afterHooks": [],
          "tests": [
            {
              "title": "visits the app root url",
              "fullTitle": "Main Menu Tabs visits the app root url",
              "timedOut": null,
              "duration": 2780,
              "state": "passed",
              "speed": "fast",
              "pass": true,
              "fail": false,
              "pending": false,
              "context": "\"videos//common/AppMenuExperienceTabs.spec.ts.mp4\"",
              "code": "cy.visit(\"/\");",
              "err": {},
              "uuid": "27ead936-2245-4699-988e-eee5f10fc2dc",
              "parentUUID": "5dd99340-ecb7-42bf-b492-ceb290f3f65b",
              "isHook": false,
              "skipped": false
            },
            {
              "title": "login as default user",
              "fullTitle": "Main Menu Tabs login as default user",
              "timedOut": null,
              "duration": 785,
              "state": "passed",
              "speed": "fast",
              "pass": true,
              "fail": false,
              "pending": false,
              "context": "\"videos//common/AppMenuExperienceTabs.spec.ts.mp4\"",
              "code": "cy.get(\".login\").should(\"be.visible\").find(\".submit-button\").click();",
              "err": {},
              "uuid": "be07cb7f-17d0-4b02-a9b8-01c1550b7b2e",
              "parentUUID": "5dd99340-ecb7-42bf-b492-ceb290f3f65b",
              "isHook": false,
              "skipped": false
            },
            {
              "title": "Has Project tab in main menu.",
              "fullTitle": "Main Menu Tabs Has Project tab in main menu.",
              "timedOut": null,
              "duration": 365,
              "state": "passed",
              "speed": "fast",
              "pass": true,
              "fail": false,
              "pending": false,
              "context": "\"videos//common/AppMenuExperienceTabs.spec.ts.mp4\"",
              "code": "cy.get(\".main-menu-wrapper\")\n    .should(\"be.visible\")\n    .and(function ($menu) {\n    expect($menu.find(\".p-tabmenuitem\")).to.contain(\"Project\");\n});",
              "err": {},
              "uuid": "89047c3f-ad5c-442c-8e05-e5390b17c697",
              "parentUUID": "5dd99340-ecb7-42bf-b492-ceb290f3f65b",
              "isHook": false,
              "skipped": false
            },
            {
              "title": "Has Setting Button",
              "fullTitle": "Main Menu Tabs Has Setting Button",
              "timedOut": null,
              "duration": 1283,
              "state": "passed",
              "speed": "fast",
              "pass": true,
              "fail": false,
              "pending": false,
              "context": "\"videos//common/AppMenuExperienceTabs.spec.ts.mp4\"",
              "code": "cy.get(\".sidebar-fixed-items\").eq(1).click();\ncy.contains(\"General\").click();\ncy.get(\".general-settings\").contains(\"Experimental Features\");\ncy.get(\".p-inputswitch-slider\").eq(0).click();\ncy.get(\".p-inputswitch-slider\").eq(1).click();\ncy.get(\".p-inputswitch-slider\").eq(2).click();\ncy.get(\".p-inputswitch-slider\").eq(3).click();\ncy.get(\".p-dialog-header-close-icon\").click();",
              "err": {},
              "uuid": "01f7fb46-2262-42ad-a480-b98a0f7553af",
              "parentUUID": "5dd99340-ecb7-42bf-b492-ceb290f3f65b",
              "isHook": false,
              "skipped": false
            },
            {
              "title": "Has Charts tab in main menu.",
              "fullTitle": "Main Menu Tabs Has Charts tab in main menu.",
              "timedOut": null,
              "duration": 85,
              "state": "passed",
              "speed": "fast",
              "pass": true,
              "fail": false,
              "pending": false,
              "context": "\"videos//common/AppMenuExperienceTabs.spec.ts.mp4\"",
              "code": "cy.get(\".main-menu-wrapper\")\n    .should(\"be.visible\")\n    .and(function ($menu) {\n    expect($menu.find(\".p-tabmenuitem\")).to.contain(\"Charts\");\n});",
              "err": {},
              "uuid": "9ea5d8e3-eb0c-4a6a-9e5d-288b9fdc0b0d",
              "parentUUID": "5dd99340-ecb7-42bf-b492-ceb290f3f65b",
              "isHook": false,
              "skipped": false
            },
            {
              "title": "Has Maps tab in main menu.",
              "fullTitle": "Main Menu Tabs Has Maps tab in main menu.",
              "timedOut": null,
              "duration": 66,
              "state": "passed",
              "speed": "fast",
              "pass": true,
              "fail": false,
              "pending": false,
              "context": "\"videos//common/AppMenuExperienceTabs.spec.ts.mp4\"",
              "code": "cy.get(\".main-menu-wrapper\")\n    .should(\"be.visible\")\n    .and(function ($menu) {\n    expect($menu.find(\".p-tabmenuitem\")).to.contain(\"Maps\");\n});",
              "err": {},
              "uuid": "c8995667-87ed-4ce6-97f4-af29cdd72e27",
              "parentUUID": "5dd99340-ecb7-42bf-b492-ceb290f3f65b",
              "isHook": false,
              "skipped": false
            },
            {
              "title": "Has Chat tab in main menu.",
              "fullTitle": "Main Menu Tabs Has Chat tab in main menu.",
              "timedOut": null,
              "duration": 65,
              "state": "passed",
              "speed": "fast",
              "pass": true,
              "fail": false,
              "pending": false,
              "context": "\"videos//common/AppMenuExperienceTabs.spec.ts.mp4\"",
              "code": "cy.get(\".main-menu-wrapper\")\n    .should(\"be.visible\")\n    .and(function ($menu) {\n    expect($menu.find(\".p-tabmenuitem\")).to.contain(\"Chat\");\n});",
              "err": {},
              "uuid": "213a2aa0-eb76-42b5-ab84-2664f9b2dafd",
              "parentUUID": "5dd99340-ecb7-42bf-b492-ceb290f3f65b",
              "isHook": false,
              "skipped": false
            },
            {
              "title": "Has Editor tab in main menu.",
              "fullTitle": "Main Menu Tabs Has Editor tab in main menu.",
              "timedOut": null,
              "duration": 82,
              "state": "passed",
              "speed": "fast",
              "pass": true,
              "fail": false,
              "pending": false,
              "context": "\"videos//common/AppMenuExperienceTabs.spec.ts.mp4\"",
              "code": "cy.get(\".main-menu-wrapper\")\n    .should(\"be.visible\")\n    .and(function ($menu) {\n    expect($menu.find(\".p-tabmenuitem\")).to.contain(\"Editor\");\n});",
              "err": {},
              "uuid": "0c2ce1a0-c6cc-4870-91b3-5af2b41f980f",
              "parentUUID": "5dd99340-ecb7-42bf-b492-ceb290f3f65b",
              "isHook": false,
              "skipped": false
            }
          ],
          "suites": [],
          "passes": [
            "27ead936-2245-4699-988e-eee5f10fc2dc",
            "be07cb7f-17d0-4b02-a9b8-01c1550b7b2e",
            "89047c3f-ad5c-442c-8e05-e5390b17c697",
            "01f7fb46-2262-42ad-a480-b98a0f7553af",
            "9ea5d8e3-eb0c-4a6a-9e5d-288b9fdc0b0d",
            "c8995667-87ed-4ce6-97f4-af29cdd72e27",
            "213a2aa0-eb76-42b5-ab84-2664f9b2dafd",
            "0c2ce1a0-c6cc-4870-91b3-5af2b41f980f"
          ],
          "failures": [],
          "pending": [],
          "skipped": [],
          "duration": 5511,
          "root": false,
          "rootEmpty": false,
          "_timeout": 2000
        }
      ],
      "passes": [],
      "failures": [],
      "pending": [],
      "skipped": [],
      "duration": 0,
      "root": true,
      "rootEmpty": true,
      "_timeout": 2000
    },
    {
      "uuid": "20d89225-ef8d-42fc-9706-d0c59c4ffb88",
      "title": "",
      "fullFile": "",
      "file": "",
      "beforeHooks": [],
      "afterHooks": [],
      "tests": [],
      "suites": [
        {
          "uuid": "4c42d0e0-d2d3-4310-861b-6285eb385b76",
          "title": "App Menu Items",
          "fullFile": "",
          "file": "",
          "beforeHooks": [],
          "afterHooks": [],
          "tests": [
            {
              "title": "visits the app root url",
              "fullTitle": "App Menu Items visits the app root url",
              "timedOut": null,
              "duration": 2260,
              "state": "passed",
              "speed": "fast",
              "pass": true,
              "fail": false,
              "pending": false,
              "context": "\"videos//common/AppMenuItems.spec.ts.mp4\"",
              "code": "cy.visit(\"/\");",
              "err": {},
              "uuid": "8e1e7e3a-9576-42ff-88ef-a2236b5f3512",
              "parentUUID": "4c42d0e0-d2d3-4310-861b-6285eb385b76",
              "isHook": false,
              "skipped": false
            },
            {
              "title": "login as default user",
              "fullTitle": "App Menu Items login as default user",
              "timedOut": null,
              "duration": 377,
              "state": "passed",
              "speed": "fast",
              "pass": true,
              "fail": false,
              "pending": false,
              "context": "\"videos//common/AppMenuItems.spec.ts.mp4\"",
              "code": "cy.get(\".login\").should(\"be.visible\").find(\".submit-button\").click();",
              "err": {},
              "uuid": "dd51568b-5223-4358-b4c5-81fec96c088c",
              "parentUUID": "4c42d0e0-d2d3-4310-861b-6285eb385b76",
              "isHook": false,
              "skipped": false
            },
            {
              "title": "Has Github link in Help menu.",
              "fullTitle": "App Menu Items Has Github link in Help menu.",
              "timedOut": null,
              "duration": 348,
              "state": "passed",
              "speed": "fast",
              "pass": true,
              "fail": false,
              "pending": false,
              "context": "\"videos//common/AppMenuItems.spec.ts.mp4\"",
              "code": "cy.get(\"#help-button\").click();\ncy.get(\".p-menu\")\n    .should(\"be.visible\")\n    .and(function ($menu) {\n    expect($menu.find(\".p-menuitem-link\")).to.contain(\"Github\");\n});\ncy.get(\"#help-button\").click();",
              "err": {},
              "uuid": "997bd3f8-307b-4a6f-9a9d-148c04d6315e",
              "parentUUID": "4c42d0e0-d2d3-4310-861b-6285eb385b76",
              "isHook": false,
              "skipped": false
            },
            {
              "title": "Has English in Change Language menu.",
              "fullTitle": "App Menu Items Has English in Change Language menu.",
              "timedOut": null,
              "duration": 304,
              "state": "passed",
              "speed": "fast",
              "pass": true,
              "fail": false,
              "pending": false,
              "context": "\"videos//common/AppMenuItems.spec.ts.mp4\"",
              "code": "cy.get(\"#change-language-button\").click();\ncy.get(\".p-menu\")\n    .should(\"be.visible\")\n    .and(function ($menu) {\n    expect($menu.find(\".p-menuitem-link\")).to.contain(\"English\");\n});\ncy.get(\"#change-language-button\").click();",
              "err": {},
              "uuid": "8f86ce98-5469-4d33-918d-f688c6db1b8f",
              "parentUUID": "4c42d0e0-d2d3-4310-861b-6285eb385b76",
              "isHook": false,
              "skipped": false
            },
            {
              "title": "Has Hindi in Change Language menu.",
              "fullTitle": "App Menu Items Has Hindi in Change Language menu.",
              "timedOut": null,
              "duration": 304,
              "state": "passed",
              "speed": "fast",
              "pass": true,
              "fail": false,
              "pending": false,
              "context": "\"videos//common/AppMenuItems.spec.ts.mp4\"",
              "code": "cy.get(\"#change-language-button\").click();\ncy.get(\".p-menu\")\n    .should(\"be.visible\")\n    .and(function ($menu) {\n    expect($menu.find(\".p-menuitem-link\")).to.contain(\"हिन्दी\");\n});\ncy.get(\"#change-language-button\").click();",
              "err": {},
              "uuid": "21dbb8e1-4033-490a-b27c-1a40853b9a8d",
              "parentUUID": "4c42d0e0-d2d3-4310-861b-6285eb385b76",
              "isHook": false,
              "skipped": false
            },
            {
              "title": "Has Toggle Theme button.",
              "fullTitle": "App Menu Items Has Toggle Theme button.",
              "timedOut": null,
              "duration": 40,
              "state": "passed",
              "speed": "fast",
              "pass": true,
              "fail": false,
              "pending": false,
              "context": "\"videos//common/AppMenuItems.spec.ts.mp4\"",
              "code": "expect(cy.get(\"#toggle-theme-button\"));",
              "err": {},
              "uuid": "5848f9a1-16a3-4084-98d7-a2389d31583b",
              "parentUUID": "4c42d0e0-d2d3-4310-861b-6285eb385b76",
              "isHook": false,
              "skipped": false
            },
            {
              "title": "Has Toggle Focus button.",
              "fullTitle": "App Menu Items Has Toggle Focus button.",
              "timedOut": null,
              "duration": 69,
              "state": "passed",
              "speed": "fast",
              "pass": true,
              "fail": false,
              "pending": false,
              "context": "\"videos//common/AppMenuItems.spec.ts.mp4\"",
              "code": "expect(cy.get(\"#toggle-focus-button\"));",
              "err": {},
              "uuid": "7262dbb5-fa46-4ddd-a462-66dd921a0ee2",
              "parentUUID": "4c42d0e0-d2d3-4310-861b-6285eb385b76",
              "isHook": false,
              "skipped": false
            },
            {
              "title": "Has Profile button.",
              "fullTitle": "App Menu Items Has Profile button.",
              "timedOut": null,
              "duration": 452,
              "state": "passed",
              "speed": "fast",
              "pass": true,
              "fail": false,
              "pending": false,
              "context": "\"videos//common/AppMenuItems.spec.ts.mp4\"",
              "code": "cy.get(\"#profile-button\").click();\ncy.get(\".p-dialog-header-close-icon\").click();",
              "err": {},
              "uuid": "f56b897f-4ca1-4db9-9d56-d6ac14cdc8bb",
              "parentUUID": "4c42d0e0-d2d3-4310-861b-6285eb385b76",
              "isHook": false,
              "skipped": false
            }
          ],
          "suites": [],
          "passes": [
            "8e1e7e3a-9576-42ff-88ef-a2236b5f3512",
            "dd51568b-5223-4358-b4c5-81fec96c088c",
            "997bd3f8-307b-4a6f-9a9d-148c04d6315e",
            "8f86ce98-5469-4d33-918d-f688c6db1b8f",
            "21dbb8e1-4033-490a-b27c-1a40853b9a8d",
            "5848f9a1-16a3-4084-98d7-a2389d31583b",
            "7262dbb5-fa46-4ddd-a462-66dd921a0ee2",
            "f56b897f-4ca1-4db9-9d56-d6ac14cdc8bb"
          ],
          "failures": [],
          "pending": [],
          "skipped": [],
          "duration": 4154,
          "root": false,
          "rootEmpty": false,
          "_timeout": 2000
        }
      ],
      "passes": [],
      "failures": [],
      "pending": [],
      "skipped": [],
      "duration": 0,
      "root": true,
      "rootEmpty": true,
      "_timeout": 2000
    },
    {
      "uuid": "41b7e318-c3eb-4da5-a8b2-489dffd3159c",
      "title": "",
      "fullFile": "",
      "file": "",
      "beforeHooks": [],
      "afterHooks": [],
      "tests": [],
      "suites": [
        {
          "uuid": "de3c4cfc-3467-4f5e-b267-96f7cca4a1d8",
          "title": "Projecty Tab",
          "fullFile": "",
          "file": "",
          "beforeHooks": [],
          "afterHooks": [],
          "tests": [
            {
              "title": "visits the app root url",
              "fullTitle": "Projecty Tab visits the app root url",
              "timedOut": null,
              "duration": 2110,
              "state": "passed",
              "speed": "fast",
              "pass": true,
              "fail": false,
              "pending": false,
              "context": "\"videos//common/ShowHideMenuBar.spec.ts.mp4\"",
              "code": "cy.visit(\"/\");",
              "err": {},
              "uuid": "d7b3b244-29e6-49f5-b72a-96b1902ba8a3",
              "parentUUID": "de3c4cfc-3467-4f5e-b267-96f7cca4a1d8",
              "isHook": false,
              "skipped": false
            },
            {
              "title": "login as default user",
              "fullTitle": "Projecty Tab login as default user",
              "timedOut": null,
              "duration": 380,
              "state": "passed",
              "speed": "fast",
              "pass": true,
              "fail": false,
              "pending": false,
              "context": "\"videos//common/ShowHideMenuBar.spec.ts.mp4\"",
              "code": "cy.get(\".login\").should(\"be.visible\").find(\".submit-button\").click();",
              "err": {},
              "uuid": "a031e6cf-490f-4076-9b78-10e0dc38893e",
              "parentUUID": "de3c4cfc-3467-4f5e-b267-96f7cca4a1d8",
              "isHook": false,
              "skipped": false
            },
            {
              "title": "Has hide menu button",
              "fullTitle": "Projecty Tab Has hide menu button",
              "timedOut": null,
              "duration": 164,
              "state": "passed",
              "speed": "fast",
              "pass": true,
              "fail": false,
              "pending": false,
              "context": "\"videos//common/ShowHideMenuBar.spec.ts.mp4\"",
              "code": "cy.get(\".main-submenu > .icon-wrapper > .pi\").click();",
              "err": {},
              "uuid": "778ac36c-34e8-4e70-9af9-a58ee83ca246",
              "parentUUID": "de3c4cfc-3467-4f5e-b267-96f7cca4a1d8",
              "isHook": false,
              "skipped": false
            },
            {
              "title": "Has Show Menubar button",
              "fullTitle": "Projecty Tab Has Show Menubar button",
              "timedOut": null,
              "duration": 175,
              "state": "passed",
              "speed": "fast",
              "pass": true,
              "fail": false,
              "pending": false,
              "context": "\"videos//common/ShowHideMenuBar.spec.ts.mp4\"",
              "code": "cy.get(\"#show-menu-bar-button\").click();",
              "err": {},
              "uuid": "3672a4ad-09a4-4f10-b3b9-86e8656ecee1",
              "parentUUID": "de3c4cfc-3467-4f5e-b267-96f7cca4a1d8",
              "isHook": false,
              "skipped": false
            }
          ],
          "suites": [],
          "passes": [
            "d7b3b244-29e6-49f5-b72a-96b1902ba8a3",
            "a031e6cf-490f-4076-9b78-10e0dc38893e",
            "778ac36c-34e8-4e70-9af9-a58ee83ca246",
            "3672a4ad-09a4-4f10-b3b9-86e8656ecee1"
          ],
          "failures": [],
          "pending": [],
          "skipped": [],
          "duration": 2829,
          "root": false,
          "rootEmpty": false,
          "_timeout": 2000
        }
      ],
      "passes": [],
      "failures": [],
      "pending": [],
      "skipped": [],
      "duration": 0,
      "root": true,
      "rootEmpty": true,
      "_timeout": 2000
    },
    {
      "uuid": "72bea9da-f768-4037-a7b6-d87ca8af9ad3",
      "title": "",
      "fullFile": "",
      "file": "",
      "beforeHooks": [],
      "afterHooks": [],
      "tests": [],
      "suites": [
        {
          "uuid": "2df71a5e-7d5f-4639-b02b-93427d4aedd9",
          "title": "Projecty Tab",
          "fullFile": "",
          "file": "",
          "beforeHooks": [],
          "afterHooks": [],
          "tests": [
            {
              "title": "visits the app root url",
              "fullTitle": "Projecty Tab visits the app root url",
              "timedOut": null,
              "duration": 1898,
              "state": "passed",
              "speed": "fast",
              "pass": true,
              "fail": false,
              "pending": false,
              "context": "\"videos//common/SidebarMenuItems.spec.ts.mp4\"",
              "code": "cy.visit(\"/\");",
              "err": {},
              "uuid": "49f24778-e39a-44c3-b9ac-2515b481e6e0",
              "parentUUID": "2df71a5e-7d5f-4639-b02b-93427d4aedd9",
              "isHook": false,
              "skipped": false
            },
            {
              "title": "login as default user",
              "fullTitle": "Projecty Tab login as default user",
              "timedOut": null,
              "duration": 425,
              "state": "passed",
              "speed": "fast",
              "pass": true,
              "fail": false,
              "pending": false,
              "context": "\"videos//common/SidebarMenuItems.spec.ts.mp4\"",
              "code": "cy.get(\".login\").should(\"be.visible\").find(\".submit-button\").click();",
              "err": {},
              "uuid": "4698ebb2-dc51-4bb3-be54-374ca191681d",
              "parentUUID": "2df71a5e-7d5f-4639-b02b-93427d4aedd9",
              "isHook": false,
              "skipped": false
            },
            {
              "title": "Has Setting Button",
              "fullTitle": "Projecty Tab Has Setting Button",
              "timedOut": null,
              "duration": 1030,
              "state": "passed",
              "speed": "fast",
              "pass": true,
              "fail": false,
              "pending": false,
              "context": "\"videos//common/SidebarMenuItems.spec.ts.mp4\"",
              "code": "cy.get(\".sidebar-fixed-items\").eq(1).click();\ncy.contains(\"General\").click();\ncy.contains(\"Profile\").click();\ncy.get(\".user_info-name\").contains(\"TypeRefinery User\");\ncy.contains(\"Privacy\").click();\ncy.contains(\"Services\").click();\ncy.get(\".p-dialog-header-icon\").click();",
              "err": {},
              "uuid": "48acd499-4a83-4614-a438-98c0f3607e3e",
              "parentUUID": "2df71a5e-7d5f-4639-b02b-93427d4aedd9",
              "isHook": false,
              "skipped": false
            },
            {
              "title": "Has Logout Button",
              "fullTitle": "Projecty Tab Has Logout Button",
              "timedOut": null,
              "duration": 195,
              "state": "passed",
              "speed": "fast",
              "pass": true,
              "fail": false,
              "pending": false,
              "context": "\"videos//common/SidebarMenuItems.spec.ts.mp4\"",
              "code": "cy.get(\".sidebar-fixed-items\").eq(2).click();",
              "err": {},
              "uuid": "2b6206f6-60e3-43bf-a08e-c97c2e30f684",
              "parentUUID": "2df71a5e-7d5f-4639-b02b-93427d4aedd9",
              "isHook": false,
              "skipped": false
            }
          ],
          "suites": [],
          "passes": [
            "49f24778-e39a-44c3-b9ac-2515b481e6e0",
            "4698ebb2-dc51-4bb3-be54-374ca191681d",
            "48acd499-4a83-4614-a438-98c0f3607e3e",
            "2b6206f6-60e3-43bf-a08e-c97c2e30f684"
          ],
          "failures": [],
          "pending": [],
          "skipped": [],
          "duration": 3548,
          "root": false,
          "rootEmpty": false,
          "_timeout": 2000
        }
      ],
      "passes": [],
      "failures": [],
      "pending": [],
      "skipped": [],
      "duration": 0,
      "root": true,
      "rootEmpty": true,
      "_timeout": 2000
    },
    {
      "uuid": "956623d9-8fd6-4010-85d1-6daeb6d8ec28",
      "title": "",
      "fullFile": "",
      "file": "",
      "beforeHooks": [],
      "afterHooks": [],
      "tests": [],
      "suites": [
        {
          "uuid": "7bc62f1d-a8e9-40c7-9523-d4bddd413194",
          "title": "Projecty Tab",
          "fullFile": "",
          "file": "",
          "beforeHooks": [],
          "afterHooks": [],
          "tests": [
            {
              "title": "visits the app root url",
              "fullTitle": "Projecty Tab visits the app root url",
              "timedOut": null,
              "duration": 2319,
              "state": "passed",
              "speed": "fast",
              "pass": true,
              "fail": false,
              "pending": false,
              "context": "\"videos//projects/ProjectTabHasMenuOptions.spec.ts.mp4\"",
              "code": "cy.visit(\"/\");",
              "err": {},
              "uuid": "f470cc6b-0943-43be-9d69-98ed8e64b834",
              "parentUUID": "7bc62f1d-a8e9-40c7-9523-d4bddd413194",
              "isHook": false,
              "skipped": false
            },
            {
              "title": "login as default user",
              "fullTitle": "Projecty Tab login as default user",
              "timedOut": null,
              "duration": 375,
              "state": "passed",
              "speed": "fast",
              "pass": true,
              "fail": false,
              "pending": false,
              "context": "\"videos//projects/ProjectTabHasMenuOptions.spec.ts.mp4\"",
              "code": "cy.get(\".login\").should(\"be.visible\").find(\".submit-button\").click();",
              "err": {},
              "uuid": "a5a0f711-4df8-4d65-89a8-6c8bf8ef0694",
              "parentUUID": "7bc62f1d-a8e9-40c7-9523-d4bddd413194",
              "isHook": false,
              "skipped": false
            },
            {
              "title": "Has Sub Menu Buttons.",
              "fullTitle": "Projecty Tab Has Sub Menu Buttons.",
              "timedOut": null,
              "duration": 239,
              "state": "passed",
              "speed": "fast",
              "pass": true,
              "fail": false,
              "pending": false,
              "context": "\"videos//projects/ProjectTabHasMenuOptions.spec.ts.mp4\"",
              "code": "cy.get(\".p-menuitem-link[href='#/home/project']\").click();\ncy.get(\".main-submenu\")\n    .should(\"be.visible\")\n    .and(function ($tab) {\n    expect($tab.find(\".main-submenu--item\")).to.contain(\"New Project\");\n    expect($tab.find(\".main-submenu--item\")).to.contain(\"New Query\");\n    expect($tab.find(\".main-submenu--item\")).to.contain(\"New Connection\");\n    expect($tab.find(\".main-submenu--item\")).to.contain(\"New Transformer\");\n});",
              "err": {},
              "uuid": "cfa61f4a-d448-44c9-8162-e6db5c927983",
              "parentUUID": "7bc62f1d-a8e9-40c7-9523-d4bddd413194",
              "isHook": false,
              "skipped": false
            }
          ],
          "suites": [],
          "passes": [
            "f470cc6b-0943-43be-9d69-98ed8e64b834",
            "a5a0f711-4df8-4d65-89a8-6c8bf8ef0694",
            "cfa61f4a-d448-44c9-8162-e6db5c927983"
          ],
          "failures": [],
          "pending": [],
          "skipped": [],
          "duration": 2933,
          "root": false,
          "rootEmpty": false,
          "_timeout": 2000
        }
      ],
      "passes": [],
      "failures": [],
      "pending": [],
      "skipped": [],
      "duration": 0,
      "root": true,
      "rootEmpty": true,
      "_timeout": 2000
    },
    {
      "uuid": "e281905b-35bb-47bd-a8b8-2e4ee23e54f7",
      "title": "",
      "fullFile": "",
      "file": "",
      "beforeHooks": [],
      "afterHooks": [],
      "tests": [],
      "suites": [
        {
          "uuid": "2f47c61c-afb4-4090-9a98-8e63fce93386",
          "title": "Projecty Tab",
          "fullFile": "",
          "file": "",
          "beforeHooks": [],
          "afterHooks": [],
          "tests": [
            {
              "title": "visits the app root url",
              "fullTitle": "Projecty Tab visits the app root url",
              "timedOut": null,
              "duration": 2168,
              "state": "passed",
              "speed": "fast",
              "pass": true,
              "fail": false,
              "pending": false,
              "context": "\"videos//projects/TabSubMenu.spec.ts.mp4\"",
              "code": "cy.visit(\"/\");",
              "err": {},
              "uuid": "54dd4342-9f05-44b4-8954-7b9aa1186e32",
              "parentUUID": "2f47c61c-afb4-4090-9a98-8e63fce93386",
              "isHook": false,
              "skipped": false
            },
            {
              "title": "login as default user",
              "fullTitle": "Projecty Tab login as default user",
              "timedOut": null,
              "duration": 342,
              "state": "passed",
              "speed": "fast",
              "pass": true,
              "fail": false,
              "pending": false,
              "context": "\"videos//projects/TabSubMenu.spec.ts.mp4\"",
              "code": "cy.get(\".login\").should(\"be.visible\").find(\".submit-button\").click();",
              "err": {},
              "uuid": "ed133319-5f7c-4301-8863-d13d40cd91c5",
              "parentUUID": "2f47c61c-afb4-4090-9a98-8e63fce93386",
              "isHook": false,
              "skipped": false
            }
          ],
          "suites": [],
          "passes": [
            "54dd4342-9f05-44b4-8954-7b9aa1186e32",
            "ed133319-5f7c-4301-8863-d13d40cd91c5"
          ],
          "failures": [],
          "pending": [],
          "skipped": [],
          "duration": 2510,
          "root": false,
          "rootEmpty": false,
          "_timeout": 2000
        }
      ],
      "passes": [],
      "failures": [],
      "pending": [],
      "skipped": [],
      "duration": 0,
      "root": true,
      "rootEmpty": true,
      "_timeout": 2000
    }
  ],
  "meta": {
    "mocha": {
      "version": "7.0.1"
    },
    "mochawesome": {
      "options": {
        "quiet": false,
        "reportFilename": "mochawesome",
        "saveHtml": false,
        "saveJson": true,
        "consoleReporter": "spec",
        "useInlineDiffs": false,
        "code": true
      },
      "version": "7.1.0"
    },
    "marge": {
      "options": {
        "id": "default",
        "reportDir": "cypress/results",
        "overwrite": false,
        "html": false,
        "json": true
      },
      "version": "6.1.0"
    }
  }
}